pylips/__init__.py
pylips/face/.DS_Store
pylips/face/ExpressionPresets.py
pylips/face/FacePresets.py
pylips/face/__init_.py
pylips/face/start.py
pylips/face/static/.DS_Store
pylips/face/static/css/overlay_styles.css
pylips/face/static/js/canvasFace.js
pylips/face/static/js/dat.gui.min.js
pylips/face/static/js/facecontrol.js
pylips/face/static/js/helpers.js
pylips/face/static/js/socketio.min.js
pylips/face/templates/editor.html
pylips/face/templates/index.html
pylips/speech/__init__.py
pylips/speech/client.py
pylips/speech/polly_tts.py
pylips/speech/robot_face.py
pylips/speech/system_tts.py
pylips-0.0.16.dist-info/licenses/LICENSE
pylips-0.0.16.dist-info/METADATA
pylips-0.0.16.dist-info/WHEEL
pylips-0.0.16.dist-info/top_level.txt
pylips-0.0.16.dist-info/RECORD
